iotfunctions/__init__.py
iotfunctions/aggregate.py
iotfunctions/anomaly.py
iotfunctions/automation.py
iotfunctions/base.py
iotfunctions/bif.py
iotfunctions/data_quality.py
iotfunctions/db.py
iotfunctions/dbhelper.py
iotfunctions/dbtables.py
iotfunctions/engine.py
iotfunctions/enginelog.py
iotfunctions/entity.py
iotfunctions/estimator.py
iotfunctions/exceptions.py
iotfunctions/generator.py
iotfunctions/loader.py
iotfunctions/metadata.py
iotfunctions/pipeline.py
iotfunctions/sample.py
iotfunctions/stages.py
iotfunctions/system_function.py
iotfunctions/ui.py
iotfunctions/util.py
iotfunctions-9.0.0.dist-info/METADATA
iotfunctions-9.0.0.dist-info/WHEEL
iotfunctions-9.0.0.dist-info/top_level.txt
iotfunctions-9.0.0.dist-info/RECORD
