Metadata-Version: 2.1
Name: iotfunctions
Version: 9.0.0
Summary: Open source component of the Maximo Asset Manager pipeline
Home-page: https://github.com/ibm-watson-iot/iotfunctions
Author: Sivakumar Rajendren
Author-email: rsiva@us.ibm.com
Classifier: Programming Language :: Python :: 3
Classifier: License :: OSI Approved :: Apache Software License
Classifier: Operating System :: OS Independent
Requires-Python: >=3.6
Requires-Dist: certifi >=2023.7.22
Requires-Dist: dill ==0.3.6
Requires-Dist: ibm-watson-machine-learning ==1.0.333
Requires-Dist: ibm-db ==3.1.4
Requires-Dist: ibm-db-sa ==0.3.9
Requires-Dist: lightgbm ==3.3.5
Requires-Dist: lxml ==4.9.2
Requires-Dist: nose2 ==0.6.0
Requires-Dist: numpy ==1.23.5
Requires-Dist: pandas ==1.5.3
Requires-Dist: protobuf ==4.21.12
Requires-Dist: psycopg2-binary ==2.9.5
Requires-Dist: pyarrow ==14.0.1
Requires-Dist: pyod ==1.0.0
Requires-Dist: requests ==2.31.0
Requires-Dist: ruptures ==1.1.5
Requires-Dist: scikit-image ==0.19.3
Requires-Dist: scikit-learn ==1.1.1
Requires-Dist: scipy ==1.11.1
Requires-Dist: sqlalchemy ==1.4.39
Requires-Dist: statsmodels ==0.13.5
Requires-Dist: stumpy ==1.9.2
Requires-Dist: tabulate ==0.8.10
Requires-Dist: urllib3 ==1.26.18
Provides-Extra: kafka
Requires-Dist: confluent-kafka ==1.9.2 ; extra == 'kafka'
